README.md
setup.py
complex_fraction/__init__.py
complex_fraction.egg-info/PKG-INFO
complex_fraction.egg-info/SOURCES.txt
complex_fraction.egg-info/dependency_links.txt
complex_fraction.egg-info/top_level.txt
complex_fraction.egg-info/zip-safe